jinja2_components/__init__.py
jinja2_components/component.py
jinja2_components/ext.py
jinja2_components-0.0.4.dist-info/LICENSE
jinja2_components-0.0.4.dist-info/METADATA
jinja2_components-0.0.4.dist-info/WHEEL
jinja2_components-0.0.4.dist-info/RECORD
