Metadata-Version: 2.1
Name: jinja2-components
Version: 0.0.4
Summary: Streamlined way to build and reuse your Jinja2 templates from code
Home-page: https://github.com/octo-gone/jinja2-components
Author: octo-gone
Author-email: nklimin007@gmail.com
Requires-Python: >=3.8,<4.0
Classifier: Programming Language :: Python :: 3
Classifier: Programming Language :: Python :: 3.8
Classifier: Programming Language :: Python :: 3.9
Classifier: Programming Language :: Python :: 3.10
Classifier: Programming Language :: Python :: 3.11
Classifier: Programming Language :: Python :: 3.12
Requires-Dist: jinja2 (>=2.10)
Project-URL: Repository, https://github.com/octo-gone/jinja2-components
